<?xml version="1.0" ?>
<DecisionMakerBehaviour>
  <Id>626</Id>
  <Location>CommitteRoom</Location>
  <ReactionTime>00:00:10:000</ReactionTime>
  <AnswerPriorityType> DEVICE_PRIORITY </AnswerPriorityType>
  <SendPriorityType> RECEPTION_ORDER </SendPriorityType>
  <MyDevices>
    <PriorityDevice priority="1" device="FAX" send2Multiple="true" sendSeparateFromReceive="true"/>
    <PriorityDevice priority="1" device="EMAIL" send2Multiple="true" sendSeparateFromReceive="true"/>
    <PriorityDevice priority="1" device="MOBILEPHONE" send2Multiple="true" sendSeparateFromReceive="false"/>
    <PriorityDevice priority="1" device="LANDLINEPHONE" send2Multiple="true" sendSeparateFromReceive="false"/>
  </MyDevices>
  <TaskPrioritized>
    <PriorityTask priority="1" task="ANSWER"/>
    <PriorityTask priority="2" task="SEND"/>
    <PriorityTask priority="3" task="DO_ACTION"/>
  </TaskPrioritized>
      <AnswerDevicePriority>
      </AnswerDevicePriority>
  <CommunicationRelations>
    <RelationPerson id="647">
      <Device device="FAX"/>
      <Device device="EMAIL"/>
      <Device device="MOBILEPHONE"/>
      <Device device="LANDLINEPHONE"/>
    </RelationPerson>
    <RelationPerson id="650">
      <Device device="FAX"/>
      <Device device="EMAIL"/>
      <Device device="MOBILEPHONE"/>
      <Device device="LANDLINEPHONE"/>
    </RelationPerson>
    <RelationPerson id="653">
      <Device device="FAX"/>
      <Device device="EMAIL"/>
      <Device device="MOBILEPHONE"/>
      <Device device="LANDLINEPHONE"/>
    </RelationPerson>
    <RelationPerson id="656">
      <Device device="FAX"/>
      <Device device="EMAIL"/>
      <Device device="MOBILEPHONE"/>
      <Device device="LANDLINEPHONE"/>
    </RelationPerson>
    <RelationPerson id="659">
      <Device device="FAX"/>
      <Device device="EMAIL"/>
      <Device device="MOBILEPHONE"/>
      <Device device="LANDLINEPHONE"/>
    </RelationPerson>
    <RelationPerson id="662">
      <Device device="FAX"/>
      <Device device="EMAIL"/>
      <Device device="MOBILEPHONE"/>
      <Device device="LANDLINEPHONE"/>
    </RelationPerson>
    <RelationPerson id="665">
      <Device device="FAX"/>
      <Device device="EMAIL"/>
      <Device device="MOBILEPHONE"/>
      <Device device="LANDLINEPHONE"/>
    </RelationPerson>
    <RelationPerson id="668">
      <Device device="FAX"/>
      <Device device="EMAIL"/>
      <Device device="MOBILEPHONE"/>
      <Device device="LANDLINEPHONE"/>
    </RelationPerson>
    <RelationPerson id="671">
      <Device device="FAX"/>
      <Device device="EMAIL"/>
      <Device device="MOBILEPHONE"/>
      <Device device="LANDLINEPHONE"/>
    </RelationPerson>
    <RelationPerson id="674">
      <Device device="FAX"/>
      <Device device="EMAIL"/>
      <Device device="MOBILEPHONE"/>
      <Device device="LANDLINEPHONE"/>
    </RelationPerson>
    <RelationPerson id="677">
      <Device device="FAX"/>
      <Device device="EMAIL"/>
      <Device device="MOBILEPHONE"/>
      <Device device="LANDLINEPHONE"/>
    </RelationPerson>
    <RelationPerson id="680">
      <Device device="FAX"/>
      <Device device="EMAIL"/>
      <Device device="MOBILEPHONE"/>
      <Device device="LANDLINEPHONE"/>
    </RelationPerson>
    <RelationPerson id="683">
      <Device device="FAX"/>
      <Device device="EMAIL"/>
      <Device device="MOBILEPHONE"/>
      <Device device="LANDLINEPHONE"/>
    </RelationPerson>
    <RelationPerson id="686">
      <Device device="FAX"/>
      <Device device="EMAIL"/>
      <Device device="MOBILEPHONE"/>
      <Device device="LANDLINEPHONE"/>
    </RelationPerson>
    <RelationPerson id="702">
      <Device device="FAX"/>
      <Device device="EMAIL"/>
      <Device device="MOBILEPHONE"/>
      <Device device="LANDLINEPHONE"/>
    </RelationPerson>
    <RelationPerson id="718">
      <Device device="FAX"/>
      <Device device="EMAIL"/>
      <Device device="MOBILEPHONE"/>
      <Device device="LANDLINEPHONE"/>
    </RelationPerson>
    <RelationPerson id="728">
      <Device device="FAX"/>
      <Device device="EMAIL"/>
      <Device device="MOBILEPHONE"/>
      <Device device="LANDLINEPHONE"/>
    </RelationPerson>
    <RelationPerson id="744">
      <Device device="FAX"/>
      <Device device="EMAIL"/>
      <Device device="MOBILEPHONE"/>
      <Device device="LANDLINEPHONE"/>
    </RelationPerson>
    <RelationPerson id="747">
      <Device device="FAX"/>
      <Device device="EMAIL"/>
      <Device device="MOBILEPHONE"/>
      <Device device="LANDLINEPHONE"/>
    </RelationPerson>
    <RelationPerson id="750">
      <Device device="FAX"/>
      <Device device="EMAIL"/>
      <Device device="MOBILEPHONE"/>
      <Device device="LANDLINEPHONE"/>
    </RelationPerson>
    <RelationPerson id="752">
      <Device device="FAX"/>
      <Device device="EMAIL"/>
      <Device device="MOBILEPHONE"/>
      <Device device="LANDLINEPHONE"/>
    </RelationPerson>
    <RelationPerson id="754">
      <Device device="FAX"/>
      <Device device="EMAIL"/>
      <Device device="MOBILEPHONE"/>
      <Device device="LANDLINEPHONE"/>
    </RelationPerson>
    <RelationPerson id="755">
      <Device device="FAX"/>
      <Device device="EMAIL"/>
      <Device device="MOBILEPHONE"/>
      <Device device="LANDLINEPHONE"/>
    </RelationPerson>
    <RelationPerson id="756">
      <Device device="FAX"/>
      <Device device="EMAIL"/>
      <Device device="MOBILEPHONE"/>
      <Device device="LANDLINEPHONE"/>
    </RelationPerson>
    <RelationPerson id="757">
      <Device device="FAX"/>
      <Device device="EMAIL"/>
      <Device device="MOBILEPHONE"/>
      <Device device="LANDLINEPHONE"/>
    </RelationPerson>
    <RelationPerson id="758">
      <Device device="FAX"/>
      <Device device="EMAIL"/>
      <Device device="MOBILEPHONE"/>
      <Device device="LANDLINEPHONE"/>
    </RelationPerson>
    <RelationPerson id="759">
      <Device device="FAX"/>
      <Device device="EMAIL"/>
      <Device device="MOBILEPHONE"/>
      <Device device="LANDLINEPHONE"/>
    </RelationPerson>
    <RelationPerson id="760">
      <Device device="FAX"/>
      <Device device="EMAIL"/>
      <Device device="MOBILEPHONE"/>
      <Device device="LANDLINEPHONE"/>
    </RelationPerson>
    <RelationPerson id="761">
      <Device device="FAX"/>
      <Device device="EMAIL"/>
      <Device device="MOBILEPHONE"/>
      <Device device="LANDLINEPHONE"/>
    </RelationPerson>
    <RelationPerson id="762">
      <Device device="FAX"/>
      <Device device="EMAIL"/>
      <Device device="MOBILEPHONE"/>
      <Device device="LANDLINEPHONE"/>
    </RelationPerson>
    <RelationPerson id="763">
      <Device device="FAX"/>
      <Device device="EMAIL"/>
      <Device device="MOBILEPHONE"/>
      <Device device="LANDLINEPHONE"/>
    </RelationPerson>
    <RelationPerson id="764">
      <Device device="FAX"/>
      <Device device="EMAIL"/>
      <Device device="MOBILEPHONE"/>
      <Device device="LANDLINEPHONE"/>
    </RelationPerson>
    <RelationPerson id="765">
      <Device device="FAX"/>
      <Device device="EMAIL"/>
      <Device device="MOBILEPHONE"/>
      <Device device="LANDLINEPHONE"/>
    </RelationPerson>
    <RelationPerson id="766">
      <Device device="FAX"/>
      <Device device="EMAIL"/>
      <Device device="MOBILEPHONE"/>
      <Device device="LANDLINEPHONE"/>
    </RelationPerson>
    <RelationPerson id="767">
      <Device device="FAX"/>
      <Device device="EMAIL"/>
      <Device device="MOBILEPHONE"/>
      <Device device="LANDLINEPHONE"/>
    </RelationPerson>
    <RelationPerson id="768">
      <Device device="FAX"/>
      <Device device="EMAIL"/>
      <Device device="MOBILEPHONE"/>
      <Device device="LANDLINEPHONE"/>
    </RelationPerson>
    <RelationPerson id="769">
      <Device device="FAX"/>
      <Device device="EMAIL"/>
      <Device device="MOBILEPHONE"/>
      <Device device="LANDLINEPHONE"/>
    </RelationPerson>
    <RelationPerson id="770">
      <Device device="FAX"/>
      <Device device="EMAIL"/>
      <Device device="MOBILEPHONE"/>
      <Device device="LANDLINEPHONE"/>
    </RelationPerson>
    <RelationPerson id="771">
      <Device device="FAX"/>
      <Device device="EMAIL"/>
      <Device device="MOBILEPHONE"/>
      <Device device="LANDLINEPHONE"/>
    </RelationPerson>
    <RelationPerson id="772">
      <Device device="FAX"/>
      <Device device="EMAIL"/>
      <Device device="MOBILEPHONE"/>
      <Device device="LANDLINEPHONE"/>
    </RelationPerson>
    <RelationPerson id="773">
      <Device device="FAX"/>
      <Device device="EMAIL"/>
      <Device device="MOBILEPHONE"/>
      <Device device="LANDLINEPHONE"/>
    </RelationPerson>
    <RelationPerson id="774">
      <Device device="FAX"/>
      <Device device="EMAIL"/>
      <Device device="MOBILEPHONE"/>
      <Device device="LANDLINEPHONE"/>
    </RelationPerson>
    <RelationPerson id="775">
      <Device device="FAX"/>
      <Device device="EMAIL"/>
      <Device device="MOBILEPHONE"/>
      <Device device="LANDLINEPHONE"/>
    </RelationPerson>
    <RelationPerson id="776">
      <Device device="FAX"/>
      <Device device="EMAIL"/>
      <Device device="MOBILEPHONE"/>
      <Device device="LANDLINEPHONE"/>
    </RelationPerson>
    <RelationPerson id="777">
      <Device device="FAX"/>
      <Device device="EMAIL"/>
      <Device device="MOBILEPHONE"/>
      <Device device="LANDLINEPHONE"/>
    </RelationPerson>
    <RelationPerson id="778">
      <Device device="FAX"/>
      <Device device="EMAIL"/>
      <Device device="MOBILEPHONE"/>
      <Device device="LANDLINEPHONE"/>
    </RelationPerson>
    <RelationPerson id="779">
      <Device device="FAX"/>
      <Device device="EMAIL"/>
      <Device device="MOBILEPHONE"/>
      <Device device="LANDLINEPHONE"/>
    </RelationPerson>
    <RelationPerson id="780">
      <Device device="FAX"/>
      <Device device="EMAIL"/>
      <Device device="MOBILEPHONE"/>
      <Device device="LANDLINEPHONE"/>
    </RelationPerson>
    <RelationPerson id="781">
      <Device device="FAX"/>
      <Device device="EMAIL"/>
      <Device device="MOBILEPHONE"/>
      <Device device="LANDLINEPHONE"/>
    </RelationPerson>
    <RelationPerson id="782">
      <Device device="FAX"/>
      <Device device="EMAIL"/>
      <Device device="MOBILEPHONE"/>
      <Device device="LANDLINEPHONE"/>
    </RelationPerson>
    <RelationPerson id="783">
      <Device device="FAX"/>
      <Device device="EMAIL"/>
      <Device device="MOBILEPHONE"/>
      <Device device="LANDLINEPHONE"/>
    </RelationPerson>
    <RelationPerson id="784">
      <Device device="FAX"/>
      <Device device="EMAIL"/>
      <Device device="MOBILEPHONE"/>
      <Device device="LANDLINEPHONE"/>
    </RelationPerson>
    <RelationPerson id="785">
      <Device device="FAX"/>
      <Device device="EMAIL"/>
      <Device device="MOBILEPHONE"/>
      <Device device="LANDLINEPHONE"/>
    </RelationPerson>
    <RelationPerson id="786">
      <Device device="FAX"/>
      <Device device="EMAIL"/>
      <Device device="MOBILEPHONE"/>
      <Device device="LANDLINEPHONE"/>
    </RelationPerson>
    <RelationPerson id="787">
      <Device device="FAX"/>
      <Device device="EMAIL"/>
      <Device device="MOBILEPHONE"/>
      <Device device="LANDLINEPHONE"/>
    </RelationPerson>
    <RelationPerson id="788">
      <Device device="FAX"/>
      <Device device="EMAIL"/>
      <Device device="MOBILEPHONE"/>
      <Device device="LANDLINEPHONE"/>
    </RelationPerson>
    <RelationPerson id="789">
      <Device device="FAX"/>
      <Device device="EMAIL"/>
      <Device device="MOBILEPHONE"/>
      <Device device="LANDLINEPHONE"/>
    </RelationPerson>
    <RelationPerson id="790">
      <Device device="FAX"/>
      <Device device="EMAIL"/>
      <Device device="MOBILEPHONE"/>
      <Device device="LANDLINEPHONE"/>
    </RelationPerson>
    <RelationPerson id="791">
      <Device device="FAX"/>
      <Device device="EMAIL"/>
      <Device device="MOBILEPHONE"/>
      <Device device="LANDLINEPHONE"/>
    </RelationPerson>
    <RelationPerson id="792">
      <Device device="FAX"/>
      <Device device="EMAIL"/>
      <Device device="MOBILEPHONE"/>
      <Device device="LANDLINEPHONE"/>
    </RelationPerson>
    <RelationPerson id="793">
      <Device device="FAX"/>
      <Device device="EMAIL"/>
      <Device device="MOBILEPHONE"/>
      <Device device="LANDLINEPHONE"/>
    </RelationPerson>
    <RelationPerson id="794">
      <Device device="FAX"/>
      <Device device="EMAIL"/>
      <Device device="MOBILEPHONE"/>
      <Device device="LANDLINEPHONE"/>
    </RelationPerson>
    <RelationPerson id="795">
      <Device device="FAX"/>
      <Device device="EMAIL"/>
      <Device device="MOBILEPHONE"/>
      <Device device="LANDLINEPHONE"/>
    </RelationPerson>
    <RelationPerson id="796">
      <Device device="FAX"/>
      <Device device="EMAIL"/>
      <Device device="MOBILEPHONE"/>
      <Device device="LANDLINEPHONE"/>
    </RelationPerson>
    <RelationPerson id="797">
      <Device device="FAX"/>
      <Device device="EMAIL"/>
      <Device device="MOBILEPHONE"/>
      <Device device="LANDLINEPHONE"/>
    </RelationPerson>
    <RelationPerson id="798">
      <Device device="FAX"/>
      <Device device="EMAIL"/>
      <Device device="MOBILEPHONE"/>
      <Device device="LANDLINEPHONE"/>
    </RelationPerson>
    <RelationPerson id="799">
      <Device device="FAX"/>
      <Device device="EMAIL"/>
      <Device device="MOBILEPHONE"/>
      <Device device="LANDLINEPHONE"/>
    </RelationPerson>
    <RelationPerson id="800">
      <Device device="FAX"/>
      <Device device="EMAIL"/>
      <Device device="MOBILEPHONE"/>
      <Device device="LANDLINEPHONE"/>
    </RelationPerson>
    <RelationPerson id="801">
      <Device device="FAX"/>
      <Device device="EMAIL"/>
      <Device device="MOBILEPHONE"/>
      <Device device="LANDLINEPHONE"/>
    </RelationPerson>
    <RelationPerson id="802">
      <Device device="FAX"/>
      <Device device="EMAIL"/>
      <Device device="MOBILEPHONE"/>
      <Device device="LANDLINEPHONE"/>
    </RelationPerson>
    <RelationPerson id="803">
      <Device device="FAX"/>
      <Device device="EMAIL"/>
      <Device device="MOBILEPHONE"/>
      <Device device="LANDLINEPHONE"/>
    </RelationPerson>
    <RelationPerson id="804">
      <Device device="FAX"/>
      <Device device="EMAIL"/>
      <Device device="MOBILEPHONE"/>
      <Device device="LANDLINEPHONE"/>
    </RelationPerson>
    <RelationPerson id="805">
      <Device device="FAX"/>
      <Device device="EMAIL"/>
      <Device device="MOBILEPHONE"/>
      <Device device="LANDLINEPHONE"/>
    </RelationPerson>
    <RelationPerson id="806">
      <Device device="FAX"/>
      <Device device="EMAIL"/>
      <Device device="MOBILEPHONE"/>
      <Device device="LANDLINEPHONE"/>
    </RelationPerson>
    <RelationPerson id="807">
      <Device device="FAX"/>
      <Device device="EMAIL"/>
      <Device device="MOBILEPHONE"/>
      <Device device="LANDLINEPHONE"/>
    </RelationPerson>
    <RelationPerson id="808">
      <Device device="FAX"/>
      <Device device="EMAIL"/>
      <Device device="MOBILEPHONE"/>
      <Device device="LANDLINEPHONE"/>
    </RelationPerson>
  </CommunicationRelations>
  <MsgBehaviour>
  <MsgReceived from="17" content="Establish_Emergency_Level_0">
 <Msg2Send to="819" content="Establish_Emergency_Level_0" compulsory="true" send2Multiple="false">
<Device device="FAX"/>
</Msg2Send>
 <Msg2Send to="809" content="Establish_Emergency_Level_0" compulsory="true" send2Multiple="false">
<Device device="FAX"/>
</Msg2Send>
 <Msg2Send to="647" content="Establish_Emergency_Level_0" compulsory="true" send2Multiple="false">
<Device device="FAX"/>
</Msg2Send>
 <Msg2Send to="650" content="Establish_Emergency_Level_0" compulsory="true" send2Multiple="false">
<Device device="FAX"/>
</Msg2Send>
 <Msg2Send to="653" content="Establish_Emergency_Level_0" compulsory="true" send2Multiple="false">
<Device device="FAX"/>
</Msg2Send>
 <Msg2Send to="656" content="Establish_Emergency_Level_0" compulsory="true" send2Multiple="false">
<Device device="FAX"/>
</Msg2Send>
 <Msg2Send to="659" content="Establish_Emergency_Level_0" compulsory="true" send2Multiple="false">
<Device device="FAX"/>
</Msg2Send>
 <Msg2Send to="662" content="Establish_Emergency_Level_0" compulsory="true" send2Multiple="false">
<Device device="FAX"/>
</Msg2Send>
 <Msg2Send to="665" content="Establish_Emergency_Level_0" compulsory="true" send2Multiple="false">
<Device device="FAX"/>
</Msg2Send>
 <Msg2Send to="668" content="Establish_Emergency_Level_0" compulsory="true" send2Multiple="false">
<Device device="FAX"/>
</Msg2Send>
 <Msg2Send to="671" content="Establish_Emergency_Level_0" compulsory="true" send2Multiple="false">
<Device device="FAX"/>
</Msg2Send>
 <Msg2Send to="674" content="Establish_Emergency_Level_0" compulsory="true" send2Multiple="false">
<Device device="FAX"/>
</Msg2Send>
 <Msg2Send to="677" content="Establish_Emergency_Level_0" compulsory="true" send2Multiple="false">
<Device device="FAX"/>
</Msg2Send>
 <Msg2Send to="680" content="Establish_Emergency_Level_0" compulsory="true" send2Multiple="false">
<Device device="FAX"/>
</Msg2Send>
 <Msg2Send to="683" content="Establish_Emergency_Level_0" compulsory="true" send2Multiple="false">
<Device device="FAX"/>
</Msg2Send>
 <Msg2Send to="686" content="Establish_Emergency_Level_0" compulsory="true" send2Multiple="false">
<Device device="FAX"/>
</Msg2Send>
 <Msg2Send to="702" content="Establish_Emergency_Level_0" compulsory="true" send2Multiple="false">
<Device device="FAX"/>
</Msg2Send>
 <Msg2Send to="718" content="Establish_Emergency_Level_0" compulsory="true" send2Multiple="false">
<Device device="FAX"/>
</Msg2Send>
 <Msg2Send to="728" content="Establish_Emergency_Level_0" compulsory="true" send2Multiple="false">
<Device device="FAX"/>
</Msg2Send>
 <Msg2Send to="744" content="Establish_Emergency_Level_0" compulsory="true" send2Multiple="false">
<Device device="FAX"/>
</Msg2Send>
 <Msg2Send to="747" content="Establish_Emergency_Level_0" compulsory="true" send2Multiple="false">
<Device device="FAX"/>
</Msg2Send>
 <Msg2Send to="750" content="Establish_Emergency_Level_0" compulsory="true" send2Multiple="false">
<Device device="FAX"/>
</Msg2Send>
 <Msg2Send to="752" content="Establish_Emergency_Level_0" compulsory="true" send2Multiple="false">
<Device device="FAX"/>
</Msg2Send>
 <Msg2Send to="754" content="Establish_Emergency_Level_0" compulsory="true" send2Multiple="false">
<Device device="FAX"/>
</Msg2Send>
 <Msg2Send to="755" content="Establish_Emergency_Level_0" compulsory="true" send2Multiple="false">
<Device device="FAX"/>
</Msg2Send>
 <Msg2Send to="756" content="Establish_Emergency_Level_0" compulsory="true" send2Multiple="false">
<Device device="FAX"/>
</Msg2Send>
 <Msg2Send to="757" content="Establish_Emergency_Level_0" compulsory="true" send2Multiple="false">
<Device device="FAX"/>
</Msg2Send>
 <Msg2Send to="758" content="Establish_Emergency_Level_0" compulsory="true" send2Multiple="false">
<Device device="FAX"/>
</Msg2Send>
 <Msg2Send to="759" content="Establish_Emergency_Level_0" compulsory="true" send2Multiple="false">
<Device device="FAX"/>
</Msg2Send>
 <Msg2Send to="760" content="Establish_Emergency_Level_0" compulsory="true" send2Multiple="false">
<Device device="FAX"/>
</Msg2Send>
 <Msg2Send to="761" content="Establish_Emergency_Level_0" compulsory="true" send2Multiple="false">
<Device device="FAX"/>
</Msg2Send>
 <Msg2Send to="762" content="Establish_Emergency_Level_0" compulsory="true" send2Multiple="false">
<Device device="FAX"/>
</Msg2Send>
 <Msg2Send to="763" content="Establish_Emergency_Level_0" compulsory="true" send2Multiple="false">
<Device device="FAX"/>
</Msg2Send>
 <Msg2Send to="764" content="Establish_Emergency_Level_0" compulsory="true" send2Multiple="false">
<Device device="FAX"/>
</Msg2Send>
 <Msg2Send to="765" content="Establish_Emergency_Level_0" compulsory="true" send2Multiple="false">
<Device device="FAX"/>
</Msg2Send>
 <Msg2Send to="766" content="Establish_Emergency_Level_0" compulsory="true" send2Multiple="false">
<Device device="FAX"/>
</Msg2Send>
 <Msg2Send to="767" content="Establish_Emergency_Level_0" compulsory="true" send2Multiple="false">
<Device device="FAX"/>
</Msg2Send>
 <Msg2Send to="768" content="Establish_Emergency_Level_0" compulsory="true" send2Multiple="false">
<Device device="FAX"/>
</Msg2Send>
 <Msg2Send to="769" content="Establish_Emergency_Level_0" compulsory="true" send2Multiple="false">
<Device device="FAX"/>
</Msg2Send>
 <Msg2Send to="770" content="Establish_Emergency_Level_0" compulsory="true" send2Multiple="false">
<Device device="FAX"/>
</Msg2Send>
 <Msg2Send to="771" content="Establish_Emergency_Level_0" compulsory="true" send2Multiple="false">
<Device device="FAX"/>
</Msg2Send>
 <Msg2Send to="772" content="Establish_Emergency_Level_0" compulsory="true" send2Multiple="false">
<Device device="FAX"/>
</Msg2Send>
 <Msg2Send to="773" content="Establish_Emergency_Level_0" compulsory="true" send2Multiple="false">
<Device device="FAX"/>
</Msg2Send>
 <Msg2Send to="774" content="Establish_Emergency_Level_0" compulsory="true" send2Multiple="false">
<Device device="FAX"/>
</Msg2Send>
 <Msg2Send to="775" content="Establish_Emergency_Level_0" compulsory="true" send2Multiple="false">
<Device device="FAX"/>
</Msg2Send>
 <Msg2Send to="776" content="Establish_Emergency_Level_0" compulsory="true" send2Multiple="false">
<Device device="FAX"/>
</Msg2Send>
 <Msg2Send to="777" content="Establish_Emergency_Level_0" compulsory="true" send2Multiple="false">
<Device device="FAX"/>
</Msg2Send>
 <Msg2Send to="778" content="Establish_Emergency_Level_0" compulsory="true" send2Multiple="false">
<Device device="FAX"/>
</Msg2Send>
 <Msg2Send to="779" content="Establish_Emergency_Level_0" compulsory="true" send2Multiple="false">
<Device device="FAX"/>
</Msg2Send>
 <Msg2Send to="780" content="Establish_Emergency_Level_0" compulsory="true" send2Multiple="false">
<Device device="FAX"/>
</Msg2Send>
 <Msg2Send to="781" content="Establish_Emergency_Level_0" compulsory="true" send2Multiple="false">
<Device device="FAX"/>
</Msg2Send>
 <Msg2Send to="782" content="Establish_Emergency_Level_0" compulsory="true" send2Multiple="false">
<Device device="FAX"/>
</Msg2Send>
 <Msg2Send to="783" content="Establish_Emergency_Level_0" compulsory="true" send2Multiple="false">
<Device device="FAX"/>
</Msg2Send>
 <Msg2Send to="784" content="Establish_Emergency_Level_0" compulsory="true" send2Multiple="false">
<Device device="FAX"/>
</Msg2Send>
 <Msg2Send to="785" content="Establish_Emergency_Level_0" compulsory="true" send2Multiple="false">
<Device device="FAX"/>
</Msg2Send>
 <Msg2Send to="786" content="Establish_Emergency_Level_0" compulsory="true" send2Multiple="false">
<Device device="FAX"/>
</Msg2Send>
 <Msg2Send to="787" content="Establish_Emergency_Level_0" compulsory="true" send2Multiple="false">
<Device device="FAX"/>
</Msg2Send>
 <Msg2Send to="788" content="Establish_Emergency_Level_0" compulsory="true" send2Multiple="false">
<Device device="FAX"/>
</Msg2Send>
 <Msg2Send to="789" content="Establish_Emergency_Level_0" compulsory="true" send2Multiple="false">
<Device device="FAX"/>
</Msg2Send>
  </MsgReceived>
  <MsgReceived from="17" content="Establish_Emergency_Level_1">
 <Msg2Send to="819" content="Establish_Emergency_Level_1" compulsory="true" send2Multiple="false">
<Device device="FAX"/>
</Msg2Send>
 <Msg2Send to="809" content="Establish_Emergency_Level_1" compulsory="true" send2Multiple="false">
<Device device="FAX"/>
</Msg2Send>
 <Msg2Send to="647" content="Establish_Emergency_Level_1" compulsory="true" send2Multiple="false">
<Device device="FAX"/>
</Msg2Send>
 <Msg2Send to="650" content="Establish_Emergency_Level_1" compulsory="true" send2Multiple="false">
<Device device="FAX"/>
</Msg2Send>
 <Msg2Send to="653" content="Establish_Emergency_Level_1" compulsory="true" send2Multiple="false">
<Device device="FAX"/>
</Msg2Send>
 <Msg2Send to="656" content="Establish_Emergency_Level_1" compulsory="true" send2Multiple="false">
<Device device="FAX"/>
</Msg2Send>
 <Msg2Send to="659" content="Establish_Emergency_Level_1" compulsory="true" send2Multiple="false">
<Device device="FAX"/>
</Msg2Send>
 <Msg2Send to="662" content="Establish_Emergency_Level_1" compulsory="true" send2Multiple="false">
<Device device="FAX"/>
</Msg2Send>
 <Msg2Send to="665" content="Establish_Emergency_Level_1" compulsory="true" send2Multiple="false">
<Device device="FAX"/>
</Msg2Send>
 <Msg2Send to="668" content="Establish_Emergency_Level_1" compulsory="true" send2Multiple="false">
<Device device="FAX"/>
</Msg2Send>
 <Msg2Send to="671" content="Establish_Emergency_Level_1" compulsory="true" send2Multiple="false">
<Device device="FAX"/>
</Msg2Send>
 <Msg2Send to="674" content="Establish_Emergency_Level_1" compulsory="true" send2Multiple="false">
<Device device="FAX"/>
</Msg2Send>
 <Msg2Send to="677" content="Establish_Emergency_Level_1" compulsory="true" send2Multiple="false">
<Device device="FAX"/>
</Msg2Send>
 <Msg2Send to="680" content="Establish_Emergency_Level_1" compulsory="true" send2Multiple="false">
<Device device="FAX"/>
</Msg2Send>
 <Msg2Send to="683" content="Establish_Emergency_Level_1" compulsory="true" send2Multiple="false">
<Device device="FAX"/>
</Msg2Send>
 <Msg2Send to="686" content="Establish_Emergency_Level_1" compulsory="true" send2Multiple="false">
<Device device="FAX"/>
</Msg2Send>
 <Msg2Send to="702" content="Establish_Emergency_Level_1" compulsory="true" send2Multiple="false">
<Device device="FAX"/>
</Msg2Send>
 <Msg2Send to="718" content="Establish_Emergency_Level_1" compulsory="true" send2Multiple="false">
<Device device="FAX"/>
</Msg2Send>
 <Msg2Send to="728" content="Establish_Emergency_Level_1" compulsory="true" send2Multiple="false">
<Device device="FAX"/>
</Msg2Send>
 <Msg2Send to="744" content="Establish_Emergency_Level_1" compulsory="true" send2Multiple="false">
<Device device="FAX"/>
</Msg2Send>
 <Msg2Send to="747" content="Establish_Emergency_Level_1" compulsory="true" send2Multiple="false">
<Device device="FAX"/>
</Msg2Send>
 <Msg2Send to="750" content="Establish_Emergency_Level_1" compulsory="true" send2Multiple="false">
<Device device="FAX"/>
</Msg2Send>
 <Msg2Send to="752" content="Establish_Emergency_Level_1" compulsory="true" send2Multiple="false">
<Device device="FAX"/>
</Msg2Send>
 <Msg2Send to="754" content="Establish_Emergency_Level_1" compulsory="true" send2Multiple="false">
<Device device="FAX"/>
</Msg2Send>
 <Msg2Send to="755" content="Establish_Emergency_Level_1" compulsory="true" send2Multiple="false">
<Device device="FAX"/>
</Msg2Send>
 <Msg2Send to="756" content="Establish_Emergency_Level_1" compulsory="true" send2Multiple="false">
<Device device="FAX"/>
</Msg2Send>
 <Msg2Send to="757" content="Establish_Emergency_Level_1" compulsory="true" send2Multiple="false">
<Device device="FAX"/>
</Msg2Send>
 <Msg2Send to="758" content="Establish_Emergency_Level_1" compulsory="true" send2Multiple="false">
<Device device="FAX"/>
</Msg2Send>
 <Msg2Send to="759" content="Establish_Emergency_Level_1" compulsory="true" send2Multiple="false">
<Device device="FAX"/>
</Msg2Send>
 <Msg2Send to="760" content="Establish_Emergency_Level_1" compulsory="true" send2Multiple="false">
<Device device="FAX"/>
</Msg2Send>
 <Msg2Send to="761" content="Establish_Emergency_Level_1" compulsory="true" send2Multiple="false">
<Device device="FAX"/>
</Msg2Send>
 <Msg2Send to="762" content="Establish_Emergency_Level_1" compulsory="true" send2Multiple="false">
<Device device="FAX"/>
</Msg2Send>
 <Msg2Send to="763" content="Establish_Emergency_Level_1" compulsory="true" send2Multiple="false">
<Device device="FAX"/>
</Msg2Send>
 <Msg2Send to="764" content="Establish_Emergency_Level_1" compulsory="true" send2Multiple="false">
<Device device="FAX"/>
</Msg2Send>
 <Msg2Send to="765" content="Establish_Emergency_Level_1" compulsory="true" send2Multiple="false">
<Device device="FAX"/>
</Msg2Send>
 <Msg2Send to="766" content="Establish_Emergency_Level_1" compulsory="true" send2Multiple="false">
<Device device="FAX"/>
</Msg2Send>
 <Msg2Send to="767" content="Establish_Emergency_Level_1" compulsory="true" send2Multiple="false">
<Device device="FAX"/>
</Msg2Send>
 <Msg2Send to="768" content="Establish_Emergency_Level_1" compulsory="true" send2Multiple="false">
<Device device="FAX"/>
</Msg2Send>
 <Msg2Send to="769" content="Establish_Emergency_Level_1" compulsory="true" send2Multiple="false">
<Device device="FAX"/>
</Msg2Send>
 <Msg2Send to="770" content="Establish_Emergency_Level_1" compulsory="true" send2Multiple="false">
<Device device="FAX"/>
</Msg2Send>
 <Msg2Send to="771" content="Establish_Emergency_Level_1" compulsory="true" send2Multiple="false">
<Device device="FAX"/>
</Msg2Send>
 <Msg2Send to="772" content="Establish_Emergency_Level_1" compulsory="true" send2Multiple="false">
<Device device="FAX"/>
</Msg2Send>
 <Msg2Send to="773" content="Establish_Emergency_Level_1" compulsory="true" send2Multiple="false">
<Device device="FAX"/>
</Msg2Send>
 <Msg2Send to="774" content="Establish_Emergency_Level_1" compulsory="true" send2Multiple="false">
<Device device="FAX"/>
</Msg2Send>
 <Msg2Send to="775" content="Establish_Emergency_Level_1" compulsory="true" send2Multiple="false">
<Device device="FAX"/>
</Msg2Send>
 <Msg2Send to="776" content="Establish_Emergency_Level_1" compulsory="true" send2Multiple="false">
<Device device="FAX"/>
</Msg2Send>
 <Msg2Send to="777" content="Establish_Emergency_Level_1" compulsory="true" send2Multiple="false">
<Device device="FAX"/>
</Msg2Send>
 <Msg2Send to="778" content="Establish_Emergency_Level_1" compulsory="true" send2Multiple="false">
<Device device="FAX"/>
</Msg2Send>
 <Msg2Send to="779" content="Establish_Emergency_Level_1" compulsory="true" send2Multiple="false">
<Device device="FAX"/>
</Msg2Send>
 <Msg2Send to="780" content="Establish_Emergency_Level_1" compulsory="true" send2Multiple="false">
<Device device="FAX"/>
</Msg2Send>
 <Msg2Send to="781" content="Establish_Emergency_Level_1" compulsory="true" send2Multiple="false">
<Device device="FAX"/>
</Msg2Send>
 <Msg2Send to="782" content="Establish_Emergency_Level_1" compulsory="true" send2Multiple="false">
<Device device="FAX"/>
</Msg2Send>
 <Msg2Send to="783" content="Establish_Emergency_Level_1" compulsory="true" send2Multiple="false">
<Device device="FAX"/>
</Msg2Send>
 <Msg2Send to="784" content="Establish_Emergency_Level_1" compulsory="true" send2Multiple="false">
<Device device="FAX"/>
</Msg2Send>
 <Msg2Send to="785" content="Establish_Emergency_Level_1" compulsory="true" send2Multiple="false">
<Device device="FAX"/>
</Msg2Send>
 <Msg2Send to="786" content="Establish_Emergency_Level_1" compulsory="true" send2Multiple="false">
<Device device="FAX"/>
</Msg2Send>
 <Msg2Send to="787" content="Establish_Emergency_Level_1" compulsory="true" send2Multiple="false">
<Device device="FAX"/>
</Msg2Send>
 <Msg2Send to="788" content="Establish_Emergency_Level_1" compulsory="true" send2Multiple="false">
<Device device="FAX"/>
</Msg2Send>
 <Msg2Send to="789" content="Establish_Emergency_Level_1" compulsory="true" send2Multiple="false">
<Device device="FAX"/>
</Msg2Send>
  </MsgReceived>
  <MsgReceived from="17" content="Establish_Emergency_Level_2">
 <Msg2Send to="819" content="Establish_Emergency_Level_2" compulsory="true" send2Multiple="false">
<Device device="FAX"/>
</Msg2Send>
 <Msg2Send to="809" content="Establish_Emergency_Level_2" compulsory="true" send2Multiple="false">
<Device device="FAX"/>
</Msg2Send>
 <Msg2Send to="647" content="Establish_Emergency_Level_2" compulsory="true" send2Multiple="false">
<Device device="FAX"/>
</Msg2Send>
 <Msg2Send to="650" content="Establish_Emergency_Level_2" compulsory="true" send2Multiple="false">
<Device device="FAX"/>
</Msg2Send>
 <Msg2Send to="653" content="Establish_Emergency_Level_2" compulsory="true" send2Multiple="false">
<Device device="FAX"/>
</Msg2Send>
 <Msg2Send to="656" content="Establish_Emergency_Level_2" compulsory="true" send2Multiple="false">
<Device device="FAX"/>
</Msg2Send>
 <Msg2Send to="659" content="Establish_Emergency_Level_2" compulsory="true" send2Multiple="false">
<Device device="FAX"/>
</Msg2Send>
 <Msg2Send to="662" content="Establish_Emergency_Level_2" compulsory="true" send2Multiple="false">
<Device device="FAX"/>
</Msg2Send>
 <Msg2Send to="665" content="Establish_Emergency_Level_2" compulsory="true" send2Multiple="false">
<Device device="FAX"/>
</Msg2Send>
 <Msg2Send to="668" content="Establish_Emergency_Level_2" compulsory="true" send2Multiple="false">
<Device device="FAX"/>
</Msg2Send>
 <Msg2Send to="671" content="Establish_Emergency_Level_2" compulsory="true" send2Multiple="false">
<Device device="FAX"/>
</Msg2Send>
 <Msg2Send to="674" content="Establish_Emergency_Level_2" compulsory="true" send2Multiple="false">
<Device device="FAX"/>
</Msg2Send>
 <Msg2Send to="677" content="Establish_Emergency_Level_2" compulsory="true" send2Multiple="false">
<Device device="FAX"/>
</Msg2Send>
 <Msg2Send to="680" content="Establish_Emergency_Level_2" compulsory="true" send2Multiple="false">
<Device device="FAX"/>
</Msg2Send>
 <Msg2Send to="683" content="Establish_Emergency_Level_2" compulsory="true" send2Multiple="false">
<Device device="FAX"/>
</Msg2Send>
 <Msg2Send to="686" content="Establish_Emergency_Level_2" compulsory="true" send2Multiple="false">
<Device device="FAX"/>
</Msg2Send>
 <Msg2Send to="702" content="Establish_Emergency_Level_2" compulsory="true" send2Multiple="false">
<Device device="FAX"/>
</Msg2Send>
 <Msg2Send to="718" content="Establish_Emergency_Level_2" compulsory="true" send2Multiple="false">
<Device device="FAX"/>
</Msg2Send>
 <Msg2Send to="728" content="Establish_Emergency_Level_2" compulsory="true" send2Multiple="false">
<Device device="FAX"/>
</Msg2Send>
 <Msg2Send to="744" content="Establish_Emergency_Level_2" compulsory="true" send2Multiple="false">
<Device device="FAX"/>
</Msg2Send>
 <Msg2Send to="747" content="Establish_Emergency_Level_2" compulsory="true" send2Multiple="false">
<Device device="FAX"/>
</Msg2Send>
 <Msg2Send to="750" content="Establish_Emergency_Level_2" compulsory="true" send2Multiple="false">
<Device device="FAX"/>
</Msg2Send>
 <Msg2Send to="752" content="Establish_Emergency_Level_2" compulsory="true" send2Multiple="false">
<Device device="FAX"/>
</Msg2Send>
 <Msg2Send to="754" content="Establish_Emergency_Level_2" compulsory="true" send2Multiple="false">
<Device device="FAX"/>
</Msg2Send>
 <Msg2Send to="755" content="Establish_Emergency_Level_2" compulsory="true" send2Multiple="false">
<Device device="FAX"/>
</Msg2Send>
 <Msg2Send to="756" content="Establish_Emergency_Level_2" compulsory="true" send2Multiple="false">
<Device device="FAX"/>
</Msg2Send>
 <Msg2Send to="757" content="Establish_Emergency_Level_2" compulsory="true" send2Multiple="false">
<Device device="FAX"/>
</Msg2Send>
 <Msg2Send to="758" content="Establish_Emergency_Level_2" compulsory="true" send2Multiple="false">
<Device device="FAX"/>
</Msg2Send>
 <Msg2Send to="759" content="Establish_Emergency_Level_2" compulsory="true" send2Multiple="false">
<Device device="FAX"/>
</Msg2Send>
 <Msg2Send to="760" content="Establish_Emergency_Level_2" compulsory="true" send2Multiple="false">
<Device device="FAX"/>
</Msg2Send>
 <Msg2Send to="761" content="Establish_Emergency_Level_2" compulsory="true" send2Multiple="false">
<Device device="FAX"/>
</Msg2Send>
 <Msg2Send to="762" content="Establish_Emergency_Level_2" compulsory="true" send2Multiple="false">
<Device device="FAX"/>
</Msg2Send>
 <Msg2Send to="763" content="Establish_Emergency_Level_2" compulsory="true" send2Multiple="false">
<Device device="FAX"/>
</Msg2Send>
 <Msg2Send to="764" content="Establish_Emergency_Level_2" compulsory="true" send2Multiple="false">
<Device device="FAX"/>
</Msg2Send>
 <Msg2Send to="765" content="Establish_Emergency_Level_2" compulsory="true" send2Multiple="false">
<Device device="FAX"/>
</Msg2Send>
 <Msg2Send to="766" content="Establish_Emergency_Level_2" compulsory="true" send2Multiple="false">
<Device device="FAX"/>
</Msg2Send>
 <Msg2Send to="767" content="Establish_Emergency_Level_2" compulsory="true" send2Multiple="false">
<Device device="FAX"/>
</Msg2Send>
 <Msg2Send to="768" content="Establish_Emergency_Level_2" compulsory="true" send2Multiple="false">
<Device device="FAX"/>
</Msg2Send>
 <Msg2Send to="769" content="Establish_Emergency_Level_2" compulsory="true" send2Multiple="false">
<Device device="FAX"/>
</Msg2Send>
 <Msg2Send to="770" content="Establish_Emergency_Level_2" compulsory="true" send2Multiple="false">
<Device device="FAX"/>
</Msg2Send>
 <Msg2Send to="771" content="Establish_Emergency_Level_2" compulsory="true" send2Multiple="false">
<Device device="FAX"/>
</Msg2Send>
 <Msg2Send to="772" content="Establish_Emergency_Level_2" compulsory="true" send2Multiple="false">
<Device device="FAX"/>
</Msg2Send>
 <Msg2Send to="773" content="Establish_Emergency_Level_2" compulsory="true" send2Multiple="false">
<Device device="FAX"/>
</Msg2Send>
 <Msg2Send to="774" content="Establish_Emergency_Level_2" compulsory="true" send2Multiple="false">
<Device device="FAX"/>
</Msg2Send>
 <Msg2Send to="775" content="Establish_Emergency_Level_2" compulsory="true" send2Multiple="false">
<Device device="FAX"/>
</Msg2Send>
 <Msg2Send to="776" content="Establish_Emergency_Level_2" compulsory="true" send2Multiple="false">
<Device device="FAX"/>
</Msg2Send>
 <Msg2Send to="777" content="Establish_Emergency_Level_2" compulsory="true" send2Multiple="false">
<Device device="FAX"/>
</Msg2Send>
 <Msg2Send to="778" content="Establish_Emergency_Level_2" compulsory="true" send2Multiple="false">
<Device device="FAX"/>
</Msg2Send>
 <Msg2Send to="779" content="Establish_Emergency_Level_2" compulsory="true" send2Multiple="false">
<Device device="FAX"/>
</Msg2Send>
 <Msg2Send to="780" content="Establish_Emergency_Level_2" compulsory="true" send2Multiple="false">
<Device device="FAX"/>
</Msg2Send>
 <Msg2Send to="781" content="Establish_Emergency_Level_2" compulsory="true" send2Multiple="false">
<Device device="FAX"/>
</Msg2Send>
 <Msg2Send to="782" content="Establish_Emergency_Level_2" compulsory="true" send2Multiple="false">
<Device device="FAX"/>
</Msg2Send>
 <Msg2Send to="783" content="Establish_Emergency_Level_2" compulsory="true" send2Multiple="false">
<Device device="FAX"/>
</Msg2Send>
 <Msg2Send to="784" content="Establish_Emergency_Level_2" compulsory="true" send2Multiple="false">
<Device device="FAX"/>
</Msg2Send>
 <Msg2Send to="785" content="Establish_Emergency_Level_2" compulsory="true" send2Multiple="false">
<Device device="FAX"/>
</Msg2Send>
 <Msg2Send to="786" content="Establish_Emergency_Level_2" compulsory="true" send2Multiple="false">
<Device device="FAX"/>
</Msg2Send>
 <Msg2Send to="787" content="Establish_Emergency_Level_2" compulsory="true" send2Multiple="false">
<Device device="FAX"/>
</Msg2Send>
 <Msg2Send to="788" content="Establish_Emergency_Level_2" compulsory="true" send2Multiple="false">
<Device device="FAX"/>
</Msg2Send>
 <Msg2Send to="789" content="Establish_Emergency_Level_2" compulsory="true" send2Multiple="false">
<Device device="FAX"/>
</Msg2Send>
  </MsgReceived>
  <MsgReceived from="17" content="Establish_Emergency_Level_3">
 <Msg2Send to="819" content="Establish_Emergency_Level_3" compulsory="true" send2Multiple="false">
<Device device="FAX"/>
</Msg2Send>
 <Msg2Send to="809" content="Establish_Emergency_Level_3" compulsory="true" send2Multiple="false">
<Device device="FAX"/>
</Msg2Send>
 <Msg2Send to="647" content="Establish_Emergency_Level_3" compulsory="true" send2Multiple="false">
<Device device="FAX"/>
</Msg2Send>
 <Msg2Send to="650" content="Establish_Emergency_Level_3" compulsory="true" send2Multiple="false">
<Device device="FAX"/>
</Msg2Send>
 <Msg2Send to="653" content="Establish_Emergency_Level_3" compulsory="true" send2Multiple="false">
<Device device="FAX"/>
</Msg2Send>
 <Msg2Send to="656" content="Establish_Emergency_Level_3" compulsory="true" send2Multiple="false">
<Device device="FAX"/>
</Msg2Send>
 <Msg2Send to="659" content="Establish_Emergency_Level_3" compulsory="true" send2Multiple="false">
<Device device="FAX"/>
</Msg2Send>
 <Msg2Send to="662" content="Establish_Emergency_Level_3" compulsory="true" send2Multiple="false">
<Device device="FAX"/>
</Msg2Send>
 <Msg2Send to="665" content="Establish_Emergency_Level_3" compulsory="true" send2Multiple="false">
<Device device="FAX"/>
</Msg2Send>
 <Msg2Send to="668" content="Establish_Emergency_Level_3" compulsory="true" send2Multiple="false">
<Device device="FAX"/>
</Msg2Send>
 <Msg2Send to="671" content="Establish_Emergency_Level_3" compulsory="true" send2Multiple="false">
<Device device="FAX"/>
</Msg2Send>
 <Msg2Send to="674" content="Establish_Emergency_Level_3" compulsory="true" send2Multiple="false">
<Device device="FAX"/>
</Msg2Send>
 <Msg2Send to="677" content="Establish_Emergency_Level_3" compulsory="true" send2Multiple="false">
<Device device="FAX"/>
</Msg2Send>
 <Msg2Send to="680" content="Establish_Emergency_Level_3" compulsory="true" send2Multiple="false">
<Device device="FAX"/>
</Msg2Send>
 <Msg2Send to="683" content="Establish_Emergency_Level_3" compulsory="true" send2Multiple="false">
<Device device="FAX"/>
</Msg2Send>
 <Msg2Send to="686" content="Establish_Emergency_Level_3" compulsory="true" send2Multiple="false">
<Device device="FAX"/>
</Msg2Send>
 <Msg2Send to="702" content="Establish_Emergency_Level_3" compulsory="true" send2Multiple="false">
<Device device="FAX"/>
</Msg2Send>
 <Msg2Send to="718" content="Establish_Emergency_Level_3" compulsory="true" send2Multiple="false">
<Device device="FAX"/>
</Msg2Send>
 <Msg2Send to="728" content="Establish_Emergency_Level_3" compulsory="true" send2Multiple="false">
<Device device="FAX"/>
</Msg2Send>
 <Msg2Send to="744" content="Establish_Emergency_Level_3" compulsory="true" send2Multiple="false">
<Device device="FAX"/>
</Msg2Send>
 <Msg2Send to="747" content="Establish_Emergency_Level_3" compulsory="true" send2Multiple="false">
<Device device="FAX"/>
</Msg2Send>
 <Msg2Send to="750" content="Establish_Emergency_Level_3" compulsory="true" send2Multiple="false">
<Device device="FAX"/>
</Msg2Send>
 <Msg2Send to="752" content="Establish_Emergency_Level_3" compulsory="true" send2Multiple="false">
<Device device="FAX"/>
</Msg2Send>
 <Msg2Send to="754" content="Establish_Emergency_Level_3" compulsory="true" send2Multiple="false">
<Device device="FAX"/>
</Msg2Send>
 <Msg2Send to="755" content="Establish_Emergency_Level_3" compulsory="true" send2Multiple="false">
<Device device="FAX"/>
</Msg2Send>
 <Msg2Send to="756" content="Establish_Emergency_Level_3" compulsory="true" send2Multiple="false">
<Device device="FAX"/>
</Msg2Send>
 <Msg2Send to="757" content="Establish_Emergency_Level_3" compulsory="true" send2Multiple="false">
<Device device="FAX"/>
</Msg2Send>
 <Msg2Send to="758" content="Establish_Emergency_Level_3" compulsory="true" send2Multiple="false">
<Device device="FAX"/>
</Msg2Send>
 <Msg2Send to="759" content="Establish_Emergency_Level_3" compulsory="true" send2Multiple="false">
<Device device="FAX"/>
</Msg2Send>
 <Msg2Send to="760" content="Establish_Emergency_Level_3" compulsory="true" send2Multiple="false">
<Device device="FAX"/>
</Msg2Send>
 <Msg2Send to="761" content="Establish_Emergency_Level_3" compulsory="true" send2Multiple="false">
<Device device="FAX"/>
</Msg2Send>
 <Msg2Send to="762" content="Establish_Emergency_Level_3" compulsory="true" send2Multiple="false">
<Device device="FAX"/>
</Msg2Send>
 <Msg2Send to="763" content="Establish_Emergency_Level_3" compulsory="true" send2Multiple="false">
<Device device="FAX"/>
</Msg2Send>
 <Msg2Send to="764" content="Establish_Emergency_Level_3" compulsory="true" send2Multiple="false">
<Device device="FAX"/>
</Msg2Send>
 <Msg2Send to="765" content="Establish_Emergency_Level_3" compulsory="true" send2Multiple="false">
<Device device="FAX"/>
</Msg2Send>
 <Msg2Send to="766" content="Establish_Emergency_Level_3" compulsory="true" send2Multiple="false">
<Device device="FAX"/>
</Msg2Send>
 <Msg2Send to="767" content="Establish_Emergency_Level_3" compulsory="true" send2Multiple="false">
<Device device="FAX"/>
</Msg2Send>
 <Msg2Send to="768" content="Establish_Emergency_Level_3" compulsory="true" send2Multiple="false">
<Device device="FAX"/>
</Msg2Send>
 <Msg2Send to="769" content="Establish_Emergency_Level_3" compulsory="true" send2Multiple="false">
<Device device="FAX"/>
</Msg2Send>
 <Msg2Send to="770" content="Establish_Emergency_Level_3" compulsory="true" send2Multiple="false">
<Device device="FAX"/>
</Msg2Send>
 <Msg2Send to="771" content="Establish_Emergency_Level_3" compulsory="true" send2Multiple="false">
<Device device="FAX"/>
</Msg2Send>
 <Msg2Send to="772" content="Establish_Emergency_Level_3" compulsory="true" send2Multiple="false">
<Device device="FAX"/>
</Msg2Send>
 <Msg2Send to="773" content="Establish_Emergency_Level_3" compulsory="true" send2Multiple="false">
<Device device="FAX"/>
</Msg2Send>
 <Msg2Send to="774" content="Establish_Emergency_Level_3" compulsory="true" send2Multiple="false">
<Device device="FAX"/>
</Msg2Send>
 <Msg2Send to="775" content="Establish_Emergency_Level_3" compulsory="true" send2Multiple="false">
<Device device="FAX"/>
</Msg2Send>
 <Msg2Send to="776" content="Establish_Emergency_Level_3" compulsory="true" send2Multiple="false">
<Device device="FAX"/>
</Msg2Send>
 <Msg2Send to="777" content="Establish_Emergency_Level_3" compulsory="true" send2Multiple="false">
<Device device="FAX"/>
</Msg2Send>
 <Msg2Send to="778" content="Establish_Emergency_Level_3" compulsory="true" send2Multiple="false">
<Device device="FAX"/>
</Msg2Send>
 <Msg2Send to="779" content="Establish_Emergency_Level_3" compulsory="true" send2Multiple="false">
<Device device="FAX"/>
</Msg2Send>
 <Msg2Send to="780" content="Establish_Emergency_Level_3" compulsory="true" send2Multiple="false">
<Device device="FAX"/>
</Msg2Send>
 <Msg2Send to="781" content="Establish_Emergency_Level_3" compulsory="true" send2Multiple="false">
<Device device="FAX"/>
</Msg2Send>
 <Msg2Send to="782" content="Establish_Emergency_Level_3" compulsory="true" send2Multiple="false">
<Device device="FAX"/>
</Msg2Send>
 <Msg2Send to="783" content="Establish_Emergency_Level_3" compulsory="true" send2Multiple="false">
<Device device="FAX"/>
</Msg2Send>
 <Msg2Send to="784" content="Establish_Emergency_Level_3" compulsory="true" send2Multiple="false">
<Device device="FAX"/>
</Msg2Send>
 <Msg2Send to="785" content="Establish_Emergency_Level_3" compulsory="true" send2Multiple="false">
<Device device="FAX"/>
</Msg2Send>
 <Msg2Send to="786" content="Establish_Emergency_Level_3" compulsory="true" send2Multiple="false">
<Device device="FAX"/>
</Msg2Send>
 <Msg2Send to="787" content="Establish_Emergency_Level_3" compulsory="true" send2Multiple="false">
<Device device="FAX"/>
</Msg2Send>
 <Msg2Send to="788" content="Establish_Emergency_Level_3" compulsory="true" send2Multiple="false">
<Device device="FAX"/>
</Msg2Send>
 <Msg2Send to="789" content="Establish_Emergency_Level_3" compulsory="true" send2Multiple="false">
<Device device="FAX"/>
</Msg2Send>
  </MsgReceived>
  </MsgBehaviour>
  <ActionBehaviour>
  </ActionBehaviour>
</DecisionMakerBehaviour>
